<databaseChangeLog xmlns="http://www.liquibase.org/xml/ns/dbchangelog"
                   xmlns:xsi="http://www.w3.org/2001/XMLSchema-instance"
                   xsi:schemaLocation="http://www.liquibase.org/xml/ns/dbchangelog
                   http://www.liquibase.org/xml/ns/dbchangelog/dbchangelog-4.0.xsd">

    <changeSet id="1" author="me">
        <createTable tableName="Car">
            <column name="id" type="BIGINT" autoIncrement="true">
                <constraints primaryKey="true" nullable="false"></constraints>
            </column>
            <column name="brand" type="VARCHAR(255)">
                <constraints nullable="false"/>
            </column>
            <column name="model" type="VARCHAR(255)">
                <constraints nullable="false"/>
            </column>
        </createTable>
    </changeSet>
    <changeSet id="2" author="me">
        <insert tableName="Car">
            <column name="brand" value="${brand}"></column>
            <column name="model" value="${model}"></column>
        </insert>
    </changeSet>
</databaseChangeLog>